[{"__type__":"cc.SpriteFrame","content":{"name":"default_panel","texture":"d81ec8ad-247c-4e62-aa3c-d35c4193c7af","rect":[0,0,20,20],"offset":[0,0],"originalSize":[20,20],"capInsets":[4,3,4,3]}},[{"__type__":"cc.Prefab","_name":"ListView","data":{"__id__":1},"asyncLoadAssets":false},{"__type__":"cc.Node","_name":"ListView","_children":[{"__id__":2}],"_components":[{"__type__":"cc.Sprite","node":{"__id__":1},"_spriteFrame":{"__uuid__":"9bbda31e-ad49-43c9-aaf2-f7d9896bac69"},"_type":1,"_sizeMode":0},{"__id__":12}],"_prefab":{"__type__":"cc.PrefabInfo","root":{"__id__":1},"fileId":"15938mHSy5FEK60fgy5D7er"},"_color":{"__type__":"cc.Color","r":184,"g":184,"b":184},"_anchorPoint":{"__type__":"cc.Vec2","y":1},"_contentSize":{"__type__":"cc.Size","width":240,"height":100}},{"__type__":"cc.Node","_name":"view","_parent":{"__id__":1},"_children":[{"__id__":3}],"_components":[{"__type__":"cc.Mask","node":{"__id__":2}}],"_prefab":{"__type__":"cc.PrefabInfo","root":{"__id__":1},"fileId":"ea5f74GqPtOrqKKl8bX9Sgz"},"_anchorPoint":{"__type__":"cc.Vec2","y":1},"_contentSize":{"__type__":"cc.Size","width":240,"height":100}},{"__type__":"cc.Node","_name":"content","_parent":{"__id__":2},"_children":[{"__id__":4},{"__id__":5},{"__id__":6},{"__id__":7},{"__id__":8},{"__id__":9},{"__id__":10},{"__id__":11}],"_components":[{"__type__":"1ec29WNfkpI+78K3dmtU6fy","node":{"__id__":3},"scrollView":{"__id__":12}}],"_prefab":{"__type__":"cc.PrefabInfo","root":{"__id__":1},"fileId":"e9858x56YRL9b7wfhDg6aM6"},"_anchorPoint":{"__type__":"cc.Vec2","y":1},"_contentSize":{"__type__":"cc.Size","width":240,"height":500}},{"__type__":"cc.Node","_name":"item","_parent":{"__id__":3},"_components":[{"__type__":"cc.Label","node":{"__id__":4},"_useOriginalSize":false,"_actualFontSize":16,"_fontSize":16,"_lineHeight":20,"_N$string":"ScrollView content1\n\n","_N$horizontalAlign":1}],"_prefab":{"__type__":"cc.PrefabInfo","root":{"__id__":1},"fileId":"652efYV3E9KULVyMDJU0a1r"},"_anchorPoint":{"__type__":"cc.Vec2","y":1},"_contentSize":{"__type__":"cc.Size","width":140.23,"height":60}},{"__type__":"cc.Node","_name":"item","_parent":{"__id__":3},"_active":false,"_components":[{"__type__":"cc.Label","node":{"__id__":5},"_useOriginalSize":false,"_actualFontSize":16,"_fontSize":16,"_lineHeight":20,"_N$string":"ScrollView content2\n\n","_N$horizontalAlign":1}],"_prefab":{"__type__":"cc.PrefabInfo","root":{"__id__":1},"fileId":"e29efQv4wRIpIacrudvxkMX"},"_anchorPoint":{"__type__":"cc.Vec2","y":1},"_contentSize":{"__type__":"cc.Size","width":140.23,"height":60},"_position":{"__type__":"cc.Vec2","y":-20}},{"__type__":"cc.Node","_name":"item","_parent":{"__id__":3},"_active":false,"_components":[{"__type__":"cc.Label","node":{"__id__":6},"_useOriginalSize":false,"_actualFontSize":16,"_fontSize":16,"_lineHeight":20,"_N$string":"ScrollView content3\n\n","_N$horizontalAlign":1}],"_prefab":{"__type__":"cc.PrefabInfo","root":{"__id__":1},"fileId":"9dfb4SJPE5DaqViIGOzPbko"},"_anchorPoint":{"__type__":"cc.Vec2","y":1},"_contentSize":{"__type__":"cc.Size","width":140.23,"height":60},"_position":{"__type__":"cc.Vec2","y":-40}},{"__type__":"cc.Node","_name":"item","_parent":{"__id__":3},"_active":false,"_components":[{"__type__":"cc.Label","node":{"__id__":7},"_useOriginalSize":false,"_actualFontSize":16,"_fontSize":16,"_lineHeight":20,"_N$string":"ScrollView content4\n\n","_N$horizontalAlign":1}],"_prefab":{"__type__":"cc.PrefabInfo","root":{"__id__":1},"fileId":"a5801dRr6tHd6JIr4uqlRrj"},"_anchorPoint":{"__type__":"cc.Vec2","y":1},"_contentSize":{"__type__":"cc.Size","width":140.23,"height":60},"_position":{"__type__":"cc.Vec2","y":-60}},{"__type__":"cc.Node","_name":"item","_parent":{"__id__":3},"_active":false,"_components":[{"__type__":"cc.Label","node":{"__id__":8},"_useOriginalSize":false,"_actualFontSize":16,"_fontSize":16,"_lineHeight":20,"_N$string":"ScrollView content5\n\n","_N$horizontalAlign":1}],"_prefab":{"__type__":"cc.PrefabInfo","root":{"__id__":1},"fileId":"204882TiupFmp8aM47o5OHN"},"_anchorPoint":{"__type__":"cc.Vec2","y":1},"_contentSize":{"__type__":"cc.Size","width":140.23,"height":60},"_position":{"__type__":"cc.Vec2","y":-80}},{"__type__":"cc.Node","_name":"item","_parent":{"__id__":3},"_active":false,"_components":[{"__type__":"cc.Label","node":{"__id__":9},"_useOriginalSize":false,"_actualFontSize":16,"_fontSize":16,"_lineHeight":20,"_N$string":"ScrollView content6\n\n","_N$horizontalAlign":1}],"_prefab":{"__type__":"cc.PrefabInfo","root":{"__id__":1},"fileId":"6482f9V6ttE8aGsx3QKe4sk"},"_anchorPoint":{"__type__":"cc.Vec2","y":1},"_contentSize":{"__type__":"cc.Size","width":140.23,"height":60},"_position":{"__type__":"cc.Vec2","y":-100}},{"__type__":"cc.Node","_name":"item","_parent":{"__id__":3},"_active":false,"_components":[{"__type__":"cc.Label","node":{"__id__":10},"_useOriginalSize":false,"_actualFontSize":16,"_fontSize":16,"_lineHeight":20,"_N$string":"ScrollView content7\n\n","_N$horizontalAlign":1}],"_prefab":{"__type__":"cc.PrefabInfo","root":{"__id__":1},"fileId":"dafbbI4tj5LjqnTNfK6iQSK"},"_anchorPoint":{"__type__":"cc.Vec2","y":1},"_contentSize":{"__type__":"cc.Size","width":140.23,"height":60},"_position":{"__type__":"cc.Vec2","y":-120}},{"__type__":"cc.Node","_name":"item","_parent":{"__id__":3},"_active":false,"_components":[{"__type__":"cc.Label","node":{"__id__":11},"_useOriginalSize":false,"_actualFontSize":16,"_fontSize":16,"_lineHeight":20,"_N$string":"ScrollView content8\n\n","_N$horizontalAlign":1}],"_prefab":{"__type__":"cc.PrefabInfo","root":{"__id__":1},"fileId":"d0cdboFzh9OC6AfT0O1zQrC"},"_anchorPoint":{"__type__":"cc.Vec2","y":1},"_contentSize":{"__type__":"cc.Size","width":140.23,"height":60},"_position":{"__type__":"cc.Vec2","y":-140}},{"__type__":"cc.ScrollView","node":{"__id__":1},"content":{"__id__":3},"horizontal":false,"inertia":false,"brake":0.75,"bounceDuration":0.23,"_N$horizontalScrollBar":null,"_N$verticalScrollBar":null}]]